{
  "expenses": [
    {
      "id": 0,
      "category": "Utility",
      "description": "Electricity",
      "value": 500,
      "date": "01/01/1970"
    },
    {
      "id": 2,
      "category": "Food",
      "description": "Apples , Milk , Oil",
      "value": 200,
      "date": "01/01/1970"
    },
    {
      "id": 3,
      "category": "Food",
      "description": "Meat and fish",
      "value": 260,
      "date": "01/01/1970"
    },
    {
      "id": 4,
      "category": "Utility",
      "description": "Gas",
      "value": 400,
      "date": "01/01/1970"
    },
    {
      "id": 5,
      "category": "Other",
      "description": "Fuel",
      "value": 800,
      "date": "01/01/1970"
    }
  ]
}